GeiIosKaifazheDeSketchRumenjiaocheng/README.md
GeiIosKaifazheDeSketchRumenjiaocheng/__init__.py
GeiIosKaifazheDeSketchRumenjiaocheng/__main__.py
GeiIosKaifazheDeSketchRumenjiaocheng/file.epub
GeiIosKaifazheDeSketchRumenjiaocheng/index.html
GeiIosKaifazheDeSketchRumenjiaocheng/css/__init__.py
GeiIosKaifazheDeSketchRumenjiaocheng/css/annotations.css
GeiIosKaifazheDeSketchRumenjiaocheng/css/main.css
GeiIosKaifazheDeSketchRumenjiaocheng/css/normalize.css
GeiIosKaifazheDeSketchRumenjiaocheng/css/popup.css
GeiIosKaifazheDeSketchRumenjiaocheng/font/__init__.py
GeiIosKaifazheDeSketchRumenjiaocheng/font/fontello.eot
GeiIosKaifazheDeSketchRumenjiaocheng/font/fontello.svg
GeiIosKaifazheDeSketchRumenjiaocheng/font/fontello.ttf
GeiIosKaifazheDeSketchRumenjiaocheng/font/fontello.woff
GeiIosKaifazheDeSketchRumenjiaocheng/img/__init__.py
GeiIosKaifazheDeSketchRumenjiaocheng/img/annotator-glyph-sprite.png
GeiIosKaifazheDeSketchRumenjiaocheng/img/annotator-icon-sprite.png
GeiIosKaifazheDeSketchRumenjiaocheng/img/apple-touch-icon.png
GeiIosKaifazheDeSketchRumenjiaocheng/img/cancelfullscreen.png
GeiIosKaifazheDeSketchRumenjiaocheng/img/close.png
GeiIosKaifazheDeSketchRumenjiaocheng/img/fullscreen.png
GeiIosKaifazheDeSketchRumenjiaocheng/img/loader.gif
GeiIosKaifazheDeSketchRumenjiaocheng/img/menu-icon.png
GeiIosKaifazheDeSketchRumenjiaocheng/img/save.png
GeiIosKaifazheDeSketchRumenjiaocheng/img/saved.png
GeiIosKaifazheDeSketchRumenjiaocheng/img/settings-s.png
GeiIosKaifazheDeSketchRumenjiaocheng/img/settings.png
GeiIosKaifazheDeSketchRumenjiaocheng/img/star.png
GeiIosKaifazheDeSketchRumenjiaocheng/js/__init__.py
GeiIosKaifazheDeSketchRumenjiaocheng/js/epub.js
GeiIosKaifazheDeSketchRumenjiaocheng/js/epub.min.js
GeiIosKaifazheDeSketchRumenjiaocheng/js/epub.min.map
GeiIosKaifazheDeSketchRumenjiaocheng/js/hooks.min.js
GeiIosKaifazheDeSketchRumenjiaocheng/js/hooks.min.map
GeiIosKaifazheDeSketchRumenjiaocheng/js/reader.js
GeiIosKaifazheDeSketchRumenjiaocheng/js/reader.js.map
gei_ios_kaifazhe_de_sketch_rumenjiaocheng-2024.3.3.0.dist-info/METADATA
gei_ios_kaifazhe_de_sketch_rumenjiaocheng-2024.3.3.0.dist-info/WHEEL
gei_ios_kaifazhe_de_sketch_rumenjiaocheng-2024.3.3.0.dist-info/entry_points.txt
gei_ios_kaifazhe_de_sketch_rumenjiaocheng-2024.3.3.0.dist-info/top_level.txt
gei_ios_kaifazhe_de_sketch_rumenjiaocheng-2024.3.3.0.dist-info/RECORD
